README
setup.py
test.py
osm_downloader/__init__.py
osm_downloader/main.py
osm_downloader.egg-info/PKG-INFO
osm_downloader.egg-info/SOURCES.txt
osm_downloader.egg-info/dependency_links.txt
osm_downloader.egg-info/entry_points.txt
osm_downloader.egg-info/requires.txt
osm_downloader.egg-info/top_level.txt