Metadata-Version: 1.0
Name: osm-downloader
Version: 0.0.1
Summary: A set of tools for downloading OSM files via the API.
Home-page: http://www.github.com/ninowalker/osm-donwloader
Author: Nino Walker
Author-email: nino.walker@gmail.com
License: MIT License.
Platform: UNKNOWN
